LICENSE
README.md
pyproject.toml
requirements.txt
remarkable_usb_web_interface_fuse/__init__.py
remarkable_usb_web_interface_fuse/__main__.py
remarkable_usb_web_interface_fuse/fuse.py
remarkable_usb_web_interface_fuse.egg-info/PKG-INFO
remarkable_usb_web_interface_fuse.egg-info/SOURCES.txt
remarkable_usb_web_interface_fuse.egg-info/dependency_links.txt
remarkable_usb_web_interface_fuse.egg-info/entry_points.txt
remarkable_usb_web_interface_fuse.egg-info/requires.txt
remarkable_usb_web_interface_fuse.egg-info/top_level.txt