Metadata-Version: 2.1
Name: remarkable_usb_web_interface_fuse
Version: 1.0.0
Summary: Userspace filesystem for remarkable usb web interface
Author-email: Eeems <eeems@eeems.email>
Classifier: Development Status :: 4 - Beta
Classifier: Environment :: Console
Classifier: Intended Audience :: Developers
Classifier: License :: OSI Approved :: MIT License
Classifier: Operating System :: POSIX :: Linux
Classifier: Programming Language :: Python :: 3 :: Only
Classifier: Programming Language :: Python :: 3
Classifier: Programming Language :: Python :: 3.11
Classifier: Programming Language :: Python :: 3.12
Classifier: Topic :: System :: Filesystems
Classifier: Topic :: Utilities
Requires-Python: >=3.11
License-File: LICENSE
Requires-Dist: fuse-python==1.0.7
Requires-Dist: requests==2.31.0
